sh_expand/__init__.py
sh_expand/bash_expand.py
sh_expand/bashrc.sh
sh_expand/env_vars_util.py
sh_expand/expand.py
sh_expand/util.py
sh_expand-0.2.1.dist-info/LICENSE
sh_expand-0.2.1.dist-info/METADATA
sh_expand-0.2.1.dist-info/WHEEL
sh_expand-0.2.1.dist-info/top_level.txt
sh_expand-0.2.1.dist-info/RECORD
