Metadata-Version: 2.2
Name: sh-expand
Version: 0.2.1
Summary: A library for expanding shell ASTs
Author-email: Michael Greenberg <michael@greenberg.science>, Konstantinos Kallas <konstantinos.kallas@hotmail.com>
License: MIT License
Project-URL: Homepage, https://github.com/binpash/sh-expand
Project-URL: Bug Tracker, https://github.com/binpash/sh-expand/issues
Classifier: Programming Language :: Python :: 3
Classifier: Topic :: System :: System Shells
Classifier: License :: OSI Approved :: MIT License
Classifier: Operating System :: POSIX
Requires-Python: >=3.8
License-File: LICENSE
Requires-Dist: shasta
Requires-Dist: pexpect
Provides-Extra: dev
Requires-Dist: libbash; extra == "dev"
Requires-Dist: libdash; extra == "dev"
Dynamic: requires-python
